odoo10_addon_account_draft_invoice_print-10.0.1.0.0.99.dev3-py2.7-nspkg.pth
odoo/addons/account_draft_invoice_print/README.rst
odoo/addons/account_draft_invoice_print/__init__.py
odoo/addons/account_draft_invoice_print/__manifest__.py
odoo/addons/account_draft_invoice_print/i18n/account_draft_invoice_print.pot
odoo/addons/account_draft_invoice_print/static/description/icon.png
odoo/addons/account_draft_invoice_print/views/invoice_view.xml
odoo10_addon_account_draft_invoice_print-10.0.1.0.0.99.dev3.dist-info/DESCRIPTION.rst
odoo10_addon_account_draft_invoice_print-10.0.1.0.0.99.dev3.dist-info/METADATA
odoo10_addon_account_draft_invoice_print-10.0.1.0.0.99.dev3.dist-info/RECORD
odoo10_addon_account_draft_invoice_print-10.0.1.0.0.99.dev3.dist-info/WHEEL
odoo10_addon_account_draft_invoice_print-10.0.1.0.0.99.dev3.dist-info/metadata.json
odoo10_addon_account_draft_invoice_print-10.0.1.0.0.99.dev3.dist-info/namespace_packages.txt
odoo10_addon_account_draft_invoice_print-10.0.1.0.0.99.dev3.dist-info/top_level.txt
